LICENSE
MANIFEST.in
README.rst
setup.py
docs/Makefile
docs/conf.py
docs/index.rst
docs/make.bat
docs/yawf.management.commands.rst
docs/yawf.management.rst
docs/yawf.message_log.rst
docs/yawf.messages.rst
docs/yawf.resources.rst
docs/yawf.revision.migrations.rst
docs/yawf.revision.rst
docs/yawf.rst
docs/yawf.tests.rst
requirements/default.txt
requirements/full.txt
yawf/__init__.py
yawf/allowed.py
yawf/base.py
yawf/base_model.py
yawf/config.py
yawf/creation.py
yawf/dispatch.py
yawf/effects.py
yawf/exceptions.py
yawf/forms.py
yawf/graph.py
yawf/graph_views.py
yawf/handlers.py
yawf/library.py
yawf/models.py
yawf/permissions.py
yawf/serialize_utils.py
yawf/signals.py
yawf/state_transition.py
yawf/transformation.py
yawf/utils.py
yawf/version.py
yawf/views.py
yawf/workflow.py
yawf.egg-info/PKG-INFO
yawf.egg-info/SOURCES.txt
yawf.egg-info/dependency_links.txt
yawf.egg-info/requires.txt
yawf.egg-info/top_level.txt
yawf/locale/ru/LC_MESSAGES/django.mo
yawf/locale/ru/LC_MESSAGES/django.po
yawf/management/__init__.py
yawf/management/commands/__init__.py
yawf/management/commands/graph_yawf_effects.py
yawf/management/commands/graph_yawf_handlers.py
yawf/message_log/__init__.py
yawf/message_log/admin.py
yawf/message_log/models.py
yawf/message_log/migrations/0001_initial.py
yawf/message_log/migrations/0002_add_workflow_id.py
yawf/message_log/migrations/0003_add_parent_id.py
yawf/message_log/migrations/0004_log_refactor.py
yawf/message_log/migrations/0005_fill_uuid.py
yawf/message_log/migrations/0006_unique_uuid.py
yawf/message_log/migrations/0007_add_meta_fields.py
yawf/message_log/migrations/0008_make_revision_generic.py
yawf/message_log/migrations/__init__.py
yawf/messages/__init__.py
yawf/messages/allowed.py
yawf/messages/common.py
yawf/messages/message.py
yawf/messages/spec.py
yawf/messages/submessage.py
yawf/resources/__init__.py
yawf/resources/allowed.py
yawf/resources/base.py
yawf/revision/__init__.py
yawf/revision/models.py
yawf/revision/utils.py
yawf/revision/backends/__init__.py
yawf/revision/backends/dummy.py
yawf/revision/backends/reversion.py
yawf/revision/migrations/0001_initial.py
