Metadata-Version: 1.1
Name: yawf
Version: 0.10.2
Summary: Yet Another Workflow Framework
Home-page: https://github.com/freevoid/yawf
Author: Nikolay Zakharov
Author-email: nikolay@desh.su
License: MIT
Keywords: workflow state transition fsm django
Platform: UNKNOWN
Classifier: Development Status :: 4 - Beta
Classifier: Intended Audience :: Developers
Classifier: Framework :: Django
Classifier: License :: OSI Approved :: MIT License
Classifier: Operating System :: OS Independent
Classifier: Programming Language :: Python
